mdpy/__init__.py
mdpy/ensemble.py
mdpy/environment.py
mdpy/error.py
mdpy/simulation.py
mdpy/analyser/__init__.py
mdpy/analyser/analyser_result.py
mdpy/analyser/coordination_number_analyser.py
mdpy/analyser/diffusion_analyser.py
mdpy/analyser/hydrogen_bond_analyser.py
mdpy/analyser/mobility_analyser.py
mdpy/analyser/rdf_analyser.py
mdpy/analyser/residence_time_analyser.py
mdpy/constraint/__init__.py
mdpy/constraint/charmm_angle_constraint.py
mdpy/constraint/charmm_bond_constraint.py
mdpy/constraint/charmm_dihedral_constraint.py
mdpy/constraint/charmm_improper_constraint.py
mdpy/constraint/charmm_nonbonded_constraint.py
mdpy/constraint/constraint.py
mdpy/constraint/electrostatic_constraint.py
mdpy/core/__init__.py
mdpy/core/cell_list.py
mdpy/core/particle.py
mdpy/core/state.py
mdpy/core/topology.py
mdpy/core/trajectory.py
mdpy/dumper/__init__.py
mdpy/dumper/dumper.py
mdpy/dumper/log_dumper.py
mdpy/dumper/pdb_dumper.py
mdpy/file/__init__.py
mdpy/file/charmm_param_file.py
mdpy/file/pdb_file.py
mdpy/file/psf_file.py
mdpy/forcefield/__init__.py
mdpy/forcefield/amber_forcefield.py
mdpy/forcefield/charmm_forcefield.py
mdpy/forcefield/forcefield.py
mdpy/integrator/__init__.py
mdpy/integrator/integrator.py
mdpy/integrator/langevin_integrator.py
mdpy/integrator/verlet_integrator.py
mdpy/minimizer/__init__.py
mdpy/minimizer/conjugate_gradient_minimizer.py
mdpy/minimizer/minimizer.py
mdpy/minimizer/steepest_descent_minimizer.py
mdpy/test/__init__.py
mdpy/test/conftest.py
mdpy/test/run_test.py
mdpy/test/test_analyser_result.py
mdpy/test/test_base_dimension.py
mdpy/test/test_cell_list.py
mdpy/test/test_charmm_angle_constraint.py
mdpy/test/test_charmm_bond_constraint.py
mdpy/test/test_charmm_dihedral_constraint.py
mdpy/test/test_charmm_forcefield.py
mdpy/test/test_charmm_improper_constraint.py
mdpy/test/test_charmm_nonbonded_constraint.py
mdpy/test/test_charmm_param_file.py
mdpy/test/test_check_quantity.py
mdpy/test/test_conjugate_gradient_minimizer.py
mdpy/test/test_constraint.py
mdpy1-0.2.0.dist-info/LICENSE
mdpy1-0.2.0.dist-info/METADATA
mdpy1-0.2.0.dist-info/WHEEL
mdpy1-0.2.0.dist-info/top_level.txt
mdpy1-0.2.0.dist-info/RECORD
