Metadata-Version: 2.1
Name: mdpy1
Version: 0.2.0
Summary: MDPy is a python framework for conducting highly extensible and flexible molecular dynamics simulation
Home-page: https://mdpy.net/
Author: Zhenyu Wei
Author-email: zhenyuwei99@gmail.com
License: UNKNOWN
Project-URL: Documentation, https://mdpy.net/
Project-URL: Source Code, https://github.com/mdpy-dev/mdpy
Keywords: Peptide dynamics simulation package
Platform: UNKNOWN
Classifier: Development Status :: 3 - Alpha
Classifier: Topic :: Scientific/Engineering :: Bio-Informatics
Classifier: Topic :: Scientific/Engineering :: Physics
Classifier: Topic :: Scientific/Engineering :: Chemistry
Classifier: License :: OSI Approved :: GNU General Public License v3 (GPLv3)
Classifier: Programming Language :: Python :: 3.7
Classifier: Programming Language :: Python :: 3.8
Classifier: Programming Language :: Python :: 3.9
Requires-Python: >=3.7
License-File: LICENSE
Requires-Dist: numpy (>=1.20.0)
Requires-Dist: scipy (>=1.7.0)
Requires-Dist: numba (>=0.54.0)
Requires-Dist: matplotlib (>=3.5.0)
Requires-Dist: pytest (>=6.2.0)
Requires-Dist: pytest-xdist (>=2.3.0)
